jsonmacros/__init__.py
jsonmacros/json_macro_schema.json
jsonmacros/jsonmacros.py
jsonmacros-0.0.5.dist-info/licenses/LICENSE.md
jsonmacros-0.0.5.dist-info/METADATA
jsonmacros-0.0.5.dist-info/WHEEL
jsonmacros-0.0.5.dist-info/top_level.txt
jsonmacros-0.0.5.dist-info/RECORD
