Metadata-Version: 2.4
Name: jsonmacros
Version: 0.0.5
Summary: A JSON preprocessor with macros, conditionals, and includes
Author-email: Broderick Riopelle <broderio@umich.edu>
License-Expression: BSD-3-Clause
Project-URL: Homepage, https://github.com/rix-ros/jsonmacros
Project-URL: Issues, https://github.com/rix-ros/jsonmacros/issues
Classifier: Programming Language :: Python :: 3
Classifier: Operating System :: OS Independent
Requires-Python: >=3.9
License-File: LICENSE.md
Dynamic: license-file
